pymmcore_widgets/__init__.py
pymmcore_widgets/_icons.py
pymmcore_widgets/_install_widget.py
pymmcore_widgets/_log.py
pymmcore_widgets/_util.py
pymmcore_widgets/experimental.py
pymmcore_widgets/py.typed
pymmcore_widgets/_deprecated/__init__.py
pymmcore_widgets/_deprecated/_device_widget.py
pymmcore_widgets/config_presets/__init__.py
pymmcore_widgets/config_presets/_objectives_pixel_configuration_widget.py
pymmcore_widgets/config_presets/_pixel_configuration_widget.py
pymmcore_widgets/config_presets/_group_preset_widget/__init__.py
pymmcore_widgets/config_presets/_group_preset_widget/_add_first_preset_widget.py
pymmcore_widgets/config_presets/_group_preset_widget/_add_group_widget.py
pymmcore_widgets/config_presets/_group_preset_widget/_add_preset_widget.py
pymmcore_widgets/config_presets/_group_preset_widget/_cfg_table.py
pymmcore_widgets/config_presets/_group_preset_widget/_edit_group_widget.py
pymmcore_widgets/config_presets/_group_preset_widget/_edit_preset_widget.py
pymmcore_widgets/config_presets/_group_preset_widget/_group_preset_table_widget.py
pymmcore_widgets/control/__init__.py
pymmcore_widgets/control/_camera_roi_widget.py
pymmcore_widgets/control/_channel_group_widget.py
pymmcore_widgets/control/_channel_widget.py
pymmcore_widgets/control/_exposure_widget.py
pymmcore_widgets/control/_live_button_widget.py
pymmcore_widgets/control/_load_system_cfg_widget.py
pymmcore_widgets/control/_objective_widget.py
pymmcore_widgets/control/_presets_widget.py
pymmcore_widgets/control/_q_stage_controller.py
pymmcore_widgets/control/_shutter_widget.py
pymmcore_widgets/control/_snap_button_widget.py
pymmcore_widgets/control/_stage_widget.py
pymmcore_widgets/control/_stage_explorer/__init__.py
pymmcore_widgets/control/_stage_explorer/_stage_explorer.py
pymmcore_widgets/control/_stage_explorer/_stage_position_marker.py
pymmcore_widgets/control/_stage_explorer/_stage_viewer.py
pymmcore_widgets/control/_stage_explorer/auto_zoom_to_fit_icon.svg
pymmcore_widgets-0.10.0.dist-info/METADATA
pymmcore_widgets-0.10.0.dist-info/WHEEL
pymmcore_widgets-0.10.0.dist-info/licenses/LICENSE
pymmcore_widgets-0.10.0.dist-info/RECORD
