Metadata-Version: 2.4
Name: pymmcore-widgets
Version: 0.10.0
Summary: A set of Qt-based widgets onto the pymmcore-plus model
Project-URL: Homepage, https://github.com/pymmcore-plus/pymmcore-widgets
Project-URL: Source Code, https://github.com/pymmcore-plus/pymmcore-widgets
Project-URL: Documentation, https://pymmcore-plus.github.io/pymmcore-widgets
Author-email: Federico Gasparoli <federico.gasparoli@gmail.com>, Talley Lambert <talley.lambert@gmail.com>, Ian Hunt-Isaak <ianhuntisaak@gmail.com>
License: BSD 3-Clause License
License-File: LICENSE
Classifier: Development Status :: 4 - Beta
Classifier: Environment :: X11 Applications :: Qt
Classifier: Intended Audience :: Developers
Classifier: Intended Audience :: Science/Research
Classifier: License :: OSI Approved :: BSD License
Classifier: Programming Language :: Python
Classifier: Programming Language :: Python :: 3
Classifier: Programming Language :: Python :: 3.9
Classifier: Programming Language :: Python :: 3.10
Classifier: Programming Language :: Python :: 3.11
Classifier: Programming Language :: Python :: 3.12
Classifier: Programming Language :: Python :: 3.13
Classifier: Topic :: Software Development :: Widget Sets
Classifier: Topic :: System :: Hardware
Classifier: Topic :: System :: Hardware :: Hardware Drivers
Classifier: Topic :: Utilities
Classifier: Typing :: Typed
Requires-Python: >=3.9
Requires-Dist: pymmcore-plus[cli]>=0.14.0
Requires-Dist: pyopengl>=3.1.9; platform_system == 'Darwin'
Requires-Dist: qtpy>=2.0
Requires-Dist: superqt[cmap,iconify,quantity]>=0.7.1
Requires-Dist: useq-schema>=0.7.2
Requires-Dist: vispy>=0.15.0
Provides-Extra: pyqt5
Requires-Dist: pyqt5>=5.15.11; extra == 'pyqt5'
Provides-Extra: pyqt6
Requires-Dist: pyqt6>=6.4.2; extra == 'pyqt6'
Provides-Extra: pyside2
Requires-Dist: pyside2>=5.15.2.1; extra == 'pyside2'
Provides-Extra: pyside6
Requires-Dist: pyside6==6.7.3; extra == 'pyside6'
